[
  {
    "full_name": "open-sauced/open-sauced",
    "stargazers_count": 709,
    "open_issues_count": 16,
    "forks_count": 296
  },
  {
    "full_name": "apple/ml-cvnets",
    "stargazers_count": 784,
    "open_issues_count": 14,
    "forks_count": 96
  },
  {
    "full_name": "supabase/supabase",
    "stargazers_count": 34838,
    "open_issues_count": 270,
    "forks_count": 2074
  },
  {
    "full_name": "huggingface/datasets",
    "stargazers_count": 13711,
    "open_issues_count": 541,
    "forks_count": 1748
  },
  {
    "full_name": "JuliaLang/julia",
    "stargazers_count": 39709,
    "open_issues_count": 4194,
    "forks_count": 4938
  },
  {
    "full_name": "mrdbourke/tensorflow-deep-learning",
    "stargazers_count": 2681,
    "open_issues_count": 8,
    "forks_count": 1203
  },
  {
    "full_name": "AnnMarieW/dash-app-gallery",
    "stargazers_count": 12,
    "open_issues_count": 13,
    "forks_count": 9
  },
  {
    "full_name": "PyTorchLightning/pytorch-lightning",
    "stargazers_count": 19170,
    "open_issues_count": 490,
    "forks_count": 2482
  },
  {
    "full_name": "ashikshafi08/learning_to_see_in_the_dark_Fastai",
    "stargazers_count": 4,
    "open_issues_count": 0,
    "forks_count": 0
  },
  {
    "full_name": "someshfengde/FastAI",
    "stargazers_count": 2,
    "open_issues_count": 0,
    "forks_count": 0
  },
  {
    "full_name": "ashikshafi08/Learning_Tensorflow",
    "stargazers_count": 14,
    "open_issues_count": 0,
    "forks_count": 2
  }
]